logreporter/__init__.py
logreporter/reporter.py
logreporter/reporterloghandler.py
logreporter/formatter/__init__.py
logreporter/formatter/discordreportformatter.py
logreporter/report/__init__.py
logreporter/report/abstractreporter.py
logreporter/report/discordwhreporter.py
LogReporter-0.2.0.dist-info/LICENSE
LogReporter-0.2.0.dist-info/METADATA
LogReporter-0.2.0.dist-info/WHEEL
LogReporter-0.2.0.dist-info/top_level.txt
LogReporter-0.2.0.dist-info/RECORD
