Metadata-Version: 2.1
Name: LogReporter
Version: 0.2.0
Summary: A module that posts the contents of logs to services on the Web along with the time axis.
Home-page: https://github.com/TakamiChie/LogReporter
Author: TakamiChie
Author-email: chie@onpu-tamago.net
License: MIT
Platform: UNKNOWN
Classifier: Development Status :: 4 - Beta
Classifier: Topic :: Utilities
Classifier: Programming Language :: Python :: 3.6
Classifier: Programming Language :: Python :: 3.7
Classifier: Programming Language :: Python :: 3.8
Classifier: Programming Language :: Python :: 3.9
Requires-Dist: requests
